leviticus/__init__.py
leviticus/main.py
leviticus/server.py
leviticus-0.0.0.dev0.dist-info/METADATA
leviticus-0.0.0.dev0.dist-info/WHEEL
leviticus-0.0.0.dev0.dist-info/licenses/LICENSE
leviticus-0.0.0.dev0.dist-info/RECORD
