Metadata-Version: 2.4
Name: leviticus
Version: 0.0.0.dev0
Summary: Leviticus
Author-email: Jackmin801 <ongjackm@gmail.com>
License: MIT
License-File: LICENSE
Requires-Python: >=3.8
Requires-Dist: fastapi[standard]
Requires-Dist: uvicorn[standard]
